RF23006UNO/__init__.py
RF23006UNO/metodos_numericos.py
rf23006uno-0.1.1.dist-info/licenses/LICENSE
rf23006uno-0.1.1.dist-info/METADATA
rf23006uno-0.1.1.dist-info/WHEEL
rf23006uno-0.1.1.dist-info/top_level.txt
rf23006uno-0.1.1.dist-info/RECORD
