Metadata-Version: 2.4
Name: RF23006UNO
Version: 0.1.1
Summary: Librería de métodos numéricos para resolver sistemas de ecuaciones
Home-page: https://github.com/Enrique281104/RF23006UNO
Author: Enrique Guillermo Rivera Flores
Author-email: rf23006@ues.edu.sv
Classifier: Programming Language :: Python :: 3
Classifier: License :: OSI Approved :: MIT License
Classifier: Operating System :: OS Independent
Requires-Python: >=3.6
License-File: LICENSE
Requires-Dist: numpy>=1.19.0
Dynamic: author
Dynamic: author-email
Dynamic: classifier
Dynamic: description
Dynamic: description-content-type
Dynamic: home-page
Dynamic: license-file
Dynamic: requires-dist
Dynamic: requires-python
Dynamic: summary
